maasclient/__init__.py
maasclient/auth.py
maasclient-0.4.3.dist-info/DESCRIPTION.rst
maasclient-0.4.3.dist-info/METADATA
maasclient-0.4.3.dist-info/RECORD
maasclient-0.4.3.dist-info/WHEEL
maasclient-0.4.3.dist-info/metadata.json
maasclient-0.4.3.dist-info/top_level.txt
