Metadata-Version: 2.0
Name: maasclient
Version: 0.4.3
Summary: Python 3 bindings for MAAS
Home-page: https://github.com/Ubuntu-Solutions-Engineering/maasclient
Author: Canonical Solutions Engineering
Author-email: ubuntu-dev@lists.ubuntu.com
License: AGPLv3+
Platform: UNKNOWN
Requires-Dist: bson (==0.4.1)
Requires-Dist: requests
Requires-Dist: requests-oauthlib
Requires-Dist: six
